jira_dev_tools/__init__.py
jira_dev_tools/cli.py
jira_dev_tools/client.py
jira_dev_tools/utils.py
jira_dev_tools-0.1.0.dist-info/licenses/LICENSE
jira_dev_tools-0.1.0.dist-info/METADATA
jira_dev_tools-0.1.0.dist-info/WHEEL
jira_dev_tools-0.1.0.dist-info/entry_points.txt
jira_dev_tools-0.1.0.dist-info/top_level.txt
jira_dev_tools-0.1.0.dist-info/RECORD
