Metadata-Version: 2.4
Name: jira-dev-tools
Version: 0.1.0
Summary: A tool for retrieving and caching Jira issue information
Author-email: Devin Ledesma <dxangobiz@gmail.com>
License-Expression: MIT
Project-URL: Homepage, https://github.com/dmlsthe1/jira-dev-tools
Project-URL: Bug Tracker, https://github.com/dmlsthe1/jira-dev-tools/issues
Classifier: Programming Language :: Python :: 3
Classifier: Operating System :: OS Independent
Requires-Python: >=3.7
License-File: LICENSE
Requires-Dist: jira
Requires-Dist: click
Requires-Dist: redis
Requires-Dist: rich
Requires-Dist: python-dotenv
Dynamic: license-file
